[{"id":153549,"name":"Adjuntas","name_ar":"Adjuntas","state_id":5134,"state_code":"001","state_name":"Adjuntas","country_id":178,"country_code":"PR","country_name":"Puerto Rico"},{"id":153550,"name":"Aguada","name_ar":"Aguada","state_id":5135,"state_code":"003","state_name":"Aguada","country_id":178,"country_code":"PR","country_name":"Puerto Rico"},{"id":153551,"name":"Aguadilla","name_ar":"Aguadilla","state_id":5136,"state_code":"005","state_name":"Aguadilla","country_id":178,"country_code":"PR","country_name":"Puerto Rico"},{"id":153552,"name":"Aguas Buenas","name_ar":"Aguas Buenas","state_id":5137,"state_code":"007","state_name":"Aguas Buenas","country_id":178,"country_code":"PR","country_name":"Puerto Rico"},{"id":153553,"name":"Aibonito","name_ar":"Aibonito","state_id":5138,"state_code":"009","state_name":"Aibonito","country_id":178,"country_code":"PR","country_name":"Puerto Rico"},{"id":153554,"name":"A\u00f1asco","name_ar":"A\u00f1asco","state_id":5139,"state_code":"011","state_name":"A\u00f1asco","country_id":178,"country_code":"PR","country_name":"Puerto Rico"},{"id":153555,"name":"Arecibo","name_ar":"Arecibo","state_id":5140,"state_code":"013","state_name":"Arecibo","country_id":178,"country_code":"PR","country_name":"Puerto Rico"},{"id":153556,"name":"Arroyo","name_ar":"Arroyo","state_id":5141,"state_code":"015","state_name":"Arroyo","country_id":178,"country_code":"PR","country_name":"Puerto Rico"},{"id":153557,"name":"Barceloneta","name_ar":"Barceloneta","state_id":5142,"state_code":"017","state_name":"Barceloneta","country_id":178,"country_code":"PR","country_name":"Puerto Rico"},{"id":153558,"name":"Barranquitas","name_ar":"Barranquitas","state_id":5143,"state_code":"019","state_name":"Barranquitas","country_id":178,"country_code":"PR","country_name":"Puerto Rico"},{"id":153559,"name":"Bayam\u00f3n","name_ar":"Bayam\u00f3n","state_id":5144,"state_code":"021","state_name":"Bayam\u00f3n","country_id":178,"country_code":"PR","country_name":"Puerto Rico"},{"id":153560,"name":"Cabo Rojo","name_ar":"Cabo Rojo","state_id":5145,"state_code":"023","state_name":"Cabo Rojo","country_id":178,"country_code":"PR","country_name":"Puerto Rico"},{"id":153561,"name":"Caguas","name_ar":"Caguas","state_id":5146,"state_code":"025","state_name":"Caguas","country_id":178,"country_code":"PR","country_name":"Puerto Rico"},{"id":153562,"name":"Camuy","name_ar":"Camuy","state_id":5147,"state_code":"027","state_name":"Camuy","country_id":178,"country_code":"PR","country_name":"Puerto Rico"},{"id":153563,"name":"Can\u00f3vanas","name_ar":"Can\u00f3vanas","state_id":5148,"state_code":"029","state_name":"Can\u00f3vanas","country_id":178,"country_code":"PR","country_name":"Puerto Rico"},{"id":153564,"name":"Carolina","name_ar":"Carolina","state_id":5149,"state_code":"031","state_name":"Carolina","country_id":178,"country_code":"PR","country_name":"Puerto Rico"},{"id":153565,"name":"Cata\u00f1o","name_ar":"Cata\u00f1o","state_id":5150,"state_code":"033","state_name":"Cata\u00f1o","country_id":178,"country_code":"PR","country_name":"Puerto Rico"},{"id":153566,"name":"Cayey","name_ar":"Cayey","state_id":5151,"state_code":"035","state_name":"Cayey","country_id":178,"country_code":"PR","country_name":"Puerto Rico"},{"id":153567,"name":"Ceiba","name_ar":"Ceiba","state_id":5152,"state_code":"037","state_name":"Ceiba","country_id":178,"country_code":"PR","country_name":"Puerto Rico"},{"id":153568,"name":"Ciales","name_ar":"Ciales","state_id":5153,"state_code":"039","state_name":"Ciales","country_id":178,"country_code":"PR","country_name":"Puerto Rico"},{"id":153569,"name":"Cidra","name_ar":"Cidra","state_id":5154,"state_code":"041","state_name":"Cidra","country_id":178,"country_code":"PR","country_name":"Puerto Rico"},{"id":153570,"name":"Coamo","name_ar":"Coamo","state_id":5155,"state_code":"043","state_name":"Coamo","country_id":178,"country_code":"PR","country_name":"Puerto Rico"},{"id":153571,"name":"Comer\u00edo","name_ar":"Comer\u00edo","state_id":5156,"state_code":"045","state_name":"Comer\u00edo","country_id":178,"country_code":"PR","country_name":"Puerto Rico"},{"id":153572,"name":"Corozal","name_ar":"Corozal","state_id":5157,"state_code":"047","state_name":"Corozal","country_id":178,"country_code":"PR","country_name":"Puerto Rico"},{"id":153573,"name":"Culebra","name_ar":"Culebra","state_id":5158,"state_code":"049","state_name":"Culebra","country_id":178,"country_code":"PR","country_name":"Puerto Rico"},{"id":153574,"name":"Dorado","name_ar":"Dorado","state_id":5159,"state_code":"051","state_name":"Dorado","country_id":178,"country_code":"PR","country_name":"Puerto Rico"},{"id":153575,"name":"Fajardo","name_ar":"Fajardo","state_id":5160,"state_code":"053","state_name":"Fajardo","country_id":178,"country_code":"PR","country_name":"Puerto Rico"},{"id":153576,"name":"Florida","name_ar":"Florida","state_id":5161,"state_code":"054","state_name":"Florida","country_id":178,"country_code":"PR","country_name":"Puerto Rico"},{"id":153577,"name":"Gu\u00e1nica","name_ar":"Gu\u00e1nica","state_id":5162,"state_code":"055","state_name":"Gu\u00e1nica","country_id":178,"country_code":"PR","country_name":"Puerto Rico"},{"id":153578,"name":"Guayama","name_ar":"Guayama","state_id":5163,"state_code":"057","state_name":"Guayama","country_id":178,"country_code":"PR","country_name":"Puerto Rico"},{"id":153579,"name":"Guayanilla","name_ar":"Guayanilla","state_id":5164,"state_code":"059","state_name":"Guayanilla","country_id":178,"country_code":"PR","country_name":"Puerto Rico"},{"id":153580,"name":"Guaynabo","name_ar":"Guaynabo","state_id":5165,"state_code":"061","state_name":"Guaynabo","country_id":178,"country_code":"PR","country_name":"Puerto Rico"},{"id":153581,"name":"Gurabo","name_ar":"Gurabo","state_id":5166,"state_code":"063","state_name":"Gurabo","country_id":178,"country_code":"PR","country_name":"Puerto Rico"},{"id":153582,"name":"Hatillo","name_ar":"Hatillo","state_id":5167,"state_code":"065","state_name":"Hatillo","country_id":178,"country_code":"PR","country_name":"Puerto Rico"},{"id":153583,"name":"Hormigueros","name_ar":"Hormigueros","state_id":5168,"state_code":"067","state_name":"Hormigueros","country_id":178,"country_code":"PR","country_name":"Puerto Rico"},{"id":153584,"name":"Humacao","name_ar":"Humacao","state_id":5169,"state_code":"069","state_name":"Humacao","country_id":178,"country_code":"PR","country_name":"Puerto Rico"},{"id":153585,"name":"Isabela","name_ar":"Isabela","state_id":5170,"state_code":"071","state_name":"Isabela","country_id":178,"country_code":"PR","country_name":"Puerto Rico"},{"id":153586,"name":"Jayuya","name_ar":"Jayuya","state_id":5171,"state_code":"073","state_name":"Jayuya","country_id":178,"country_code":"PR","country_name":"Puerto Rico"},{"id":153587,"name":"Juana D\u00edaz","name_ar":"Juana D\u00edaz","state_id":5172,"state_code":"075","state_name":"Juana D\u00edaz","country_id":178,"country_code":"PR","country_name":"Puerto Rico"},{"id":153588,"name":"Juncos","name_ar":"Juncos","state_id":5173,"state_code":"077","state_name":"Juncos","country_id":178,"country_code":"PR","country_name":"Puerto Rico"},{"id":153589,"name":"Lajas","name_ar":"Lajas","state_id":5174,"state_code":"079","state_name":"Lajas","country_id":178,"country_code":"PR","country_name":"Puerto Rico"},{"id":153590,"name":"Lares","name_ar":"Lares","state_id":5175,"state_code":"081","state_name":"Lares","country_id":178,"country_code":"PR","country_name":"Puerto Rico"},{"id":153591,"name":"Las Mar\u00edas","name_ar":"Las Mar\u00edas","state_id":5176,"state_code":"083","state_name":"Las Mar\u00edas","country_id":178,"country_code":"PR","country_name":"Puerto Rico"},{"id":153592,"name":"Las Piedras","name_ar":"Las Piedras","state_id":5177,"state_code":"085","state_name":"Las Piedras","country_id":178,"country_code":"PR","country_name":"Puerto Rico"},{"id":153593,"name":"Lo\u00edza","name_ar":"Lo\u00edza","state_id":5178,"state_code":"087","state_name":"Lo\u00edza","country_id":178,"country_code":"PR","country_name":"Puerto Rico"},{"id":153594,"name":"Luquillo","name_ar":"Luquillo","state_id":5179,"state_code":"089","state_name":"Luquillo","country_id":178,"country_code":"PR","country_name":"Puerto Rico"},{"id":153595,"name":"Manat\u00ed","name_ar":"Manat\u00ed","state_id":5180,"state_code":"091","state_name":"Manat\u00ed","country_id":178,"country_code":"PR","country_name":"Puerto Rico"},{"id":153596,"name":"Maricao","name_ar":"Maricao","state_id":5181,"state_code":"093","state_name":"Maricao","country_id":178,"country_code":"PR","country_name":"Puerto Rico"},{"id":153597,"name":"Maunabo","name_ar":"Maunabo","state_id":5182,"state_code":"095","state_name":"Maunabo","country_id":178,"country_code":"PR","country_name":"Puerto Rico"},{"id":153598,"name":"Mayag\u00fcez","name_ar":"Mayag\u00fcez","state_id":5183,"state_code":"097","state_name":"Mayag\u00fcez","country_id":178,"country_code":"PR","country_name":"Puerto Rico"},{"id":153599,"name":"Moca","name_ar":"Moca","state_id":5184,"state_code":"099","state_name":"Moca","country_id":178,"country_code":"PR","country_name":"Puerto Rico"},{"id":153600,"name":"Morovis","name_ar":"Morovis","state_id":5185,"state_code":"101","state_name":"Morovis","country_id":178,"country_code":"PR","country_name":"Puerto Rico"},{"id":153601,"name":"Naguabo","name_ar":"Naguabo","state_id":5186,"state_code":"103","state_name":"Naguabo","country_id":178,"country_code":"PR","country_name":"Puerto Rico"},{"id":153602,"name":"Naranjito","name_ar":"Naranjito","state_id":5187,"state_code":"105","state_name":"Naranjito","country_id":178,"country_code":"PR","country_name":"Puerto Rico"},{"id":153603,"name":"Orocovis","name_ar":"Orocovis","state_id":5188,"state_code":"107","state_name":"Orocovis","country_id":178,"country_code":"PR","country_name":"Puerto Rico"},{"id":153604,"name":"Patillas","name_ar":"Patillas","state_id":5189,"state_code":"109","state_name":"Patillas","country_id":178,"country_code":"PR","country_name":"Puerto Rico"},{"id":153605,"name":"Pe\u00f1uelas","name_ar":"Pe\u00f1uelas","state_id":5190,"state_code":"111","state_name":"Pe\u00f1uelas","country_id":178,"country_code":"PR","country_name":"Puerto Rico"},{"id":153606,"name":"Ponce","name_ar":"Ponce","state_id":5191,"state_code":"113","state_name":"Ponce","country_id":178,"country_code":"PR","country_name":"Puerto Rico"},{"id":153607,"name":"Quebradillas","name_ar":"Quebradillas","state_id":5192,"state_code":"115","state_name":"Quebradillas","country_id":178,"country_code":"PR","country_name":"Puerto Rico"},{"id":153608,"name":"Rinc\u00f3n","name_ar":"Rinc\u00f3n","state_id":5193,"state_code":"117","state_name":"Rinc\u00f3n","country_id":178,"country_code":"PR","country_name":"Puerto Rico"},{"id":153609,"name":"R\u00edo Grande","name_ar":"R\u00edo Grande","state_id":5194,"state_code":"119","state_name":"R\u00edo Grande","country_id":178,"country_code":"PR","country_name":"Puerto Rico"},{"id":153610,"name":"Sabana Grande","name_ar":"Sabana Grande","state_id":5195,"state_code":"121","state_name":"Sabana Grande","country_id":178,"country_code":"PR","country_name":"Puerto Rico"},{"id":153611,"name":"Salinas","name_ar":"Salinas","state_id":5196,"state_code":"123","state_name":"Salinas","country_id":178,"country_code":"PR","country_name":"Puerto Rico"},{"id":153612,"name":"San Germ\u00e1n","name_ar":"San Germ\u00e1n","state_id":5197,"state_code":"125","state_name":"San Germ\u00e1n","country_id":178,"country_code":"PR","country_name":"Puerto Rico"},{"id":153613,"name":"San Juan","name_ar":"San Juan","state_id":5198,"state_code":"127","state_name":"San Juan","country_id":178,"country_code":"PR","country_name":"Puerto Rico"},{"id":153614,"name":"San Lorenzo","name_ar":"San Lorenzo","state_id":5199,"state_code":"129","state_name":"San Lorenzo","country_id":178,"country_code":"PR","country_name":"Puerto Rico"},{"id":153615,"name":"San Sebasti\u00e1n","name_ar":"San Sebasti\u00e1n","state_id":5200,"state_code":"131","state_name":"San Sebasti\u00e1n","country_id":178,"country_code":"PR","country_name":"Puerto Rico"},{"id":153616,"name":"Santa Isabel","name_ar":"Santa Isabel","state_id":5201,"state_code":"133","state_name":"Santa Isabel","country_id":178,"country_code":"PR","country_name":"Puerto Rico"},{"id":153617,"name":"Toa Alta","name_ar":"Toa Alta","state_id":5202,"state_code":"135","state_name":"Toa Alta","country_id":178,"country_code":"PR","country_name":"Puerto Rico"},{"id":153618,"name":"Toa Baja","name_ar":"Toa Baja","state_id":5203,"state_code":"137","state_name":"Toa Baja","country_id":178,"country_code":"PR","country_name":"Puerto Rico"},{"id":153619,"name":"Trujillo Alto","name_ar":"Trujillo Alto","state_id":5204,"state_code":"139","state_name":"Trujillo Alto","country_id":178,"country_code":"PR","country_name":"Puerto Rico"},{"id":153620,"name":"Utuado","name_ar":"Utuado","state_id":5205,"state_code":"141","state_name":"Utuado","country_id":178,"country_code":"PR","country_name":"Puerto Rico"},{"id":153621,"name":"Vega Alta","name_ar":"Vega Alta","state_id":5206,"state_code":"143","state_name":"Vega Alta","country_id":178,"country_code":"PR","country_name":"Puerto Rico"},{"id":153622,"name":"Vega Baja","name_ar":"Vega Baja","state_id":5207,"state_code":"145","state_name":"Vega Baja","country_id":178,"country_code":"PR","country_name":"Puerto Rico"},{"id":153623,"name":"Vieques","name_ar":"Vieques","state_id":5208,"state_code":"147","state_name":"Vieques","country_id":178,"country_code":"PR","country_name":"Puerto Rico"},{"id":153624,"name":"Villalba","name_ar":"Villalba","state_id":5209,"state_code":"149","state_name":"Villalba","country_id":178,"country_code":"PR","country_name":"Puerto Rico"},{"id":153625,"name":"Yabucoa","name_ar":"Yabucoa","state_id":5210,"state_code":"151","state_name":"Yabucoa","country_id":178,"country_code":"PR","country_name":"Puerto Rico"},{"id":153626,"name":"Yauco","name_ar":"Yauco","state_id":5211,"state_code":"153","state_name":"Yauco","country_id":178,"country_code":"PR","country_name":"Puerto Rico"}]